jirascripting/__init__.py
jirascripting/auth_and_headers.py
jirascripting/create_fancy_jira_issue.py
jirascripting/create_jira_epic.py
jirascripting/create_jira_issue.py
jirascripting/create_jira_issue_with_parent.py
jirascripting/get_assignable_users.py
jirascripting/helpers.py
jirascripting-0.0.16.dist-info/LICENSE
jirascripting-0.0.16.dist-info/METADATA
jirascripting-0.0.16.dist-info/WHEEL
jirascripting-0.0.16.dist-info/top_level.txt
jirascripting-0.0.16.dist-info/RECORD
